blark/__init__.py
blark/__main__.py
blark/_version.py
blark/apischema_compat.py
blark/config.py
blark/dependency_store.py
blark/format.py
blark/html.py
blark/iec.lark
blark/input.py
blark/main.py
blark/output.py
blark/parse.py
blark/plain.py
blark/solution.py
blark/sphinxdomain.py
blark/summary.py
blark/transform.py
blark/typing.py
blark/util.py
blark/tests/__init__.py
blark/tests/conftest.py
blark/tests/test_cli.py
blark/tests/test_dependency_store.py
blark/tests/test_parsing.py
blark/tests/test_solution.py
blark/tests/test_summary.py
blark/tests/test_transformer.py
blark/tests/test_util.py
blark/tests/POUs/FB_Log.TcPOU
blark/tests/POUs/F_SetStateParams.TcPOU
blark/tests/POUs/global_version.TcPOU
blark/tests/source/and_then_or_else.st
blark/tests/source/array_initializer.st
blark/tests/source/array_of_addresses.st
blark/tests/source/array_of_arrays.st
blark/tests/source/array_of_objects.st
blark/tests/source/array_with_integer_initializer.st
blark/tests/source/commas_in_case.st
blark/tests/source/dereference_method.st
blark/tests/source/enum_with_function_calls.st
blark/tests/source/extended_union.st
blark/tests/source/fb_initializer.st
blark/tests/source/fb_w_public_access.st
blark/tests/source/object_oriented_dotaccess.st
blark/tests/source/pointer_to_pointer_to.st
blark/tests/source/repeated_declaration.st
blark/tests/source/stray_comment.st
blark/tests/source/type_and_fb.st
blark/tests/source/var_declarations_var_attrib.st
blark/tests/twincat_root/SampleLibraryA/SampleLibraryA/SampleLibraryA/POUs/FB_SampleA_Test.TcPOU
blark/tests/twincat_root/lcls-twincat-general/v2.8.1/LCLSGeneral/LCLSGeneral/POUs/Logger/FB_LogHandler.TcPOU
blark/tests/twincat_root/project_a/project_a/ProjectA/POUs/FB_ProjectA.TcPOU
blark/tests/twincat_root/project_a/project_a/ProjectA/POUs/MAIN.TcPOU
blark/tests/twincat_root/project_b/v1.0/project_b/ProjectB/POUs/MAIN.TcPOU
blark/tests/twincat_root/project_c/project_c/ProjectC/POUs/MAIN.TcPOU
blark-0.8.3.dist-info/licenses/LICENSE
blark-0.8.3.dist-info/METADATA
blark-0.8.3.dist-info/WHEEL
blark-0.8.3.dist-info/entry_points.txt
blark-0.8.3.dist-info/top_level.txt
blark-0.8.3.dist-info/RECORD
