Metadata-Version: 2.4
Name: blark
Version: 0.8.3
Summary: Beckhoff TwinCAT IEC 61131-3 parsing tools
Author: SLAC National Accelerator Laboratory
License: GPL
Requires-Python: >=3.6
License-File: LICENSE
Requires-Dist: lark>1.0
Requires-Dist: lxml
Requires-Dist: packaging
Requires-Dist: typing-extensions; python_version < "3.11"
Provides-Extra: dev
Requires-Dist: apischema; extra == "dev"
Requires-Dist: pytest; extra == "dev"
Requires-Dist: pytest-cov; extra == "dev"
Provides-Extra: doc
Requires-Dist: apischema; extra == "doc"
Requires-Dist: pytest; extra == "doc"
Requires-Dist: pytest-cov; extra == "doc"
Requires-Dist: docs-versions-menu; extra == "doc"
Requires-Dist: numpydoc; extra == "doc"
Requires-Dist: sphinx>=3.3.1; extra == "doc"
Requires-Dist: sphinx_rtd_theme; extra == "doc"
Requires-Dist: sphinxcontrib-jquery; extra == "doc"
Dynamic: author
Dynamic: description
Dynamic: description-content-type
Dynamic: license
Dynamic: license-file
Dynamic: provides-extra
Dynamic: requires-dist
Dynamic: requires-python
Dynamic: summary
